Metadata-Version: 1.1
Name: webdrivor
Version: 1.0
Summary: Modern Web Driver Tool.
Home-page: UNKNOWN
Author: helper
Author-email: UNKNOWN
License: MIT
Keywords: style
Platform: UNKNOWN
Classifier: Development Status :: 5 - Production/Stable
